LICENSE
README.md
setup.py
metasequoia_parser/__init__.py
metasequoia_parser/exceptions.py
metasequoia_parser.egg-info/PKG-INFO
metasequoia_parser.egg-info/SOURCES.txt
metasequoia_parser.egg-info/dependency_links.txt
metasequoia_parser.egg-info/top_level.txt
metasequoia_parser/common/__init__.py
metasequoia_parser/common/action.py
metasequoia_parser/common/grammar.py
metasequoia_parser/common/item.py
metasequoia_parser/common/item_set.py
metasequoia_parser/common/parser_base.py
metasequoia_parser/common/parsing_context.py
metasequoia_parser/common/symbol.py
metasequoia_parser/compiler/__init__.py
metasequoia_parser/compiler/lalr1.py
metasequoia_parser/functions/__init__.py
metasequoia_parser/functions/build_relation_between_item0_set.py
metasequoia_parser/functions/cal_all_item0_list.py
metasequoia_parser/functions/cal_core_to_item0_set_hash.py
metasequoia_parser/functions/cal_core_to_item1_set_hash.py
metasequoia_parser/functions/cal_init_and_accept_item_from_item_list.py
metasequoia_parser/functions/cal_nonterminal_all_start_terminal.py
metasequoia_parser/functions/cal_symbol_to_start_item_list_hash.py
metasequoia_parser/functions/closure_item0.py
metasequoia_parser/functions/closure_item1.py
metasequoia_parser/functions/create_lr_parsing_table_use_lalr1.py
metasequoia_parser/functions/create_lr_parsing_table_use_lr1.py
metasequoia_parser/functions/table_full_error.py
metasequoia_parser/lexical/__init__.py
metasequoia_parser/lexical/lexical_base.py
metasequoia_parser/lexical/lexical_iterator.py
metasequoia_parser/parser/__init__.py
metasequoia_parser/parser/lalr1.py
metasequoia_parser/parser/lr0.py
metasequoia_parser/parser/lr1.py
metasequoia_parser/parser/slr.py
metasequoia_parser/template/__init__.py
metasequoia_parser/template/action.py
metasequoia_parser/template/charset.py
metasequoia_parser/template/group.py
metasequoia_parser/template/rule.py
metasequoia_parser/utils/__init__.py
metasequoia_parser/utils/logger.py