Metadata-Version: 2.1
Name: metasequoia-parser
Version: 0.2.0
Summary: 水杉解析器生成器：提供了 LR(0)、SLR、LR(1)、LALR(1) 四种解析器，以及 LALR(1) 解析器生成器，可以根据定义的语法自动生成 Python 代码。
Home-page: https://github.com/ChangxingJiang/metasequoia-parser
Author: changxing
Author-email: 1278729001@qq.com
License: MIT License
Platform: all
Classifier: Intended Audience :: Developers
Classifier: Operating System :: OS Independent
Classifier: Natural Language :: Chinese (Simplified)
Classifier: Programming Language :: Python
Classifier: Programming Language :: Python :: 3.10
Classifier: Programming Language :: Python :: 3.11
Classifier: Programming Language :: Python :: 3.12
Classifier: Topic :: Software Development :: Libraries
License-File: LICENSE
